README.md
setup.py
rio_tiler_crs/__init__.py
rio_tiler_crs/reader.py
rio_tiler_crs.egg-info/PKG-INFO
rio_tiler_crs.egg-info/SOURCES.txt
rio_tiler_crs.egg-info/dependency_links.txt
rio_tiler_crs.egg-info/not-zip-safe
rio_tiler_crs.egg-info/requires.txt
rio_tiler_crs.egg-info/top_level.txt