Metadata-Version: 2.1
Name: rio-tiler-crs
Version: 2.0.2
Summary: A rio-tiler plugin to create tile for arbitraty grid
Home-page: https://github.com/cogeotiff/rio-tiler-crs
Author: Vincent Sarago
Author-email: vincent@developmentseed.org
License: MIT
Keywords: COG GIS
Platform: UNKNOWN
Classifier: Intended Audience :: Information Technology
Classifier: Intended Audience :: Science/Research
Classifier: License :: OSI Approved :: BSD License
Classifier: Programming Language :: Python :: 3.6
Classifier: Programming Language :: Python :: 3.7
Classifier: Topic :: Scientific/Engineering :: GIS
Requires-Python: >=3
Provides-Extra: test
Provides-Extra: dev
